pyfits/card.py
pyfits/column.py
pyfits/compression.pyd
pyfits/convenience.py
pyfits/core.py
pyfits/diff.py
pyfits/file.py
pyfits/fitsrec.py
pyfits/header.py
pyfits/py3compat.py
pyfits/util.py
pyfits/verify.py
pyfits/version.py
pyfits/_release.py
pyfits/__init__.py
pyfits/extern/six.py
pyfits/extern/__init__.py
pyfits/hdu/base.py
pyfits/hdu/compressed.py
pyfits/hdu/groups.py
pyfits/hdu/hdulist.py
pyfits/hdu/image.py
pyfits/hdu/nonstandard.py
pyfits/hdu/streaming.py
pyfits/hdu/table.py
pyfits/hdu/__init__.py
pyfits/scripts/fitscheck.py
pyfits/scripts/fitsdiff.py
pyfits/scripts/__init__.py
pyfits/tests/test_checksum.py
pyfits/tests/test_core.py
pyfits/tests/test_diff.py
pyfits/tests/test_division.py
pyfits/tests/test_groups.py
pyfits/tests/test_hdulist.py
pyfits/tests/test_header.py
pyfits/tests/test_image.py
pyfits/tests/test_nonstandard.py
pyfits/tests/test_structured.py
pyfits/tests/test_table.py
pyfits/tests/test_uint.py
pyfits/tests/test_util.py
pyfits/tests/util.py
pyfits/tests/__init__.py
pyfits/tests/data/arange.fits
pyfits/tests/data/ascii.fits
pyfits/tests/data/checksum.fits
pyfits/tests/data/comp.fits
pyfits/tests/data/fixed-1890.fits
pyfits/tests/data/o4sp040b0_raw.fits
pyfits/tests/data/random_groups.fits
pyfits/tests/data/scale.fits
pyfits/tests/data/stddata.fits
pyfits/tests/data/table.fits
pyfits/tests/data/tb.fits
pyfits/tests/data/test0.fits
pyfits/tests/data/zerowidth.fits
pyfits-3.3.data/scripts/fitscheck
pyfits-3.3.data/scripts/fitsdiff
pyfits-3.3.dist-info/DESCRIPTION.rst
pyfits-3.3.dist-info/entry_points.txt
pyfits-3.3.dist-info/METADATA
pyfits-3.3.dist-info/metadata.json
pyfits-3.3.dist-info/RECORD
pyfits-3.3.dist-info/top_level.txt
pyfits-3.3.dist-info/WHEEL
