Metadata-Version: 2.0
Name: pyfits
Version: 3.3
Summary: Reads FITS images and tables into numpy arrays and manipulates FITS headers
Home-page: http://www.stsci.edu/resources/software_hardware/pyfits
Author: J. C. Hsu, Paul Barrett, Christopher Hanley, James Taylor,
Requires-Dist: numpy
